__init__.py
bkmeup/__init__.py
bkmeup/bkmeup.py
bkmeup/cli.py
bkmeup-0.1.2.dist-info/LICENSE
bkmeup-0.1.2.dist-info/METADATA
bkmeup-0.1.2.dist-info/WHEEL
bkmeup-0.1.2.dist-info/entry_points.txt
bkmeup-0.1.2.dist-info/top_level.txt
bkmeup-0.1.2.dist-info/RECORD
